{"q+DBL6Ip/DUrNNhuYzaAOQ==":"mbr.jpg","gsjYRdHRUVZKKoL5D2DVIg==":"mbr.jpeg","Jvd/Hv+E6dzGxsxf1OSMGw==":"mbr-1.jpg","Rkh6VN1geuklqasa+Hps8w==":"mbr-2.jpg","OgtCKla7ZhzAplY/dXMFRQ==":"mbr-3.jpg","7cAX25vTViPzsEpxKtfgnw==":"mbr-4.jpg","Bzg68IuBcRh9sFO8XLZmEQ==":"mbr-5.jpg","3L8x5ialuZVROWzapuz4nA==":"mbr-6.jpg","5Yxz1Ro3xgEvJK27QZYsvA==":"mbr-1.jpeg","orRrDp0O7uYYPUWXMASTrg==":"mbr-2.jpeg","hNnJ/ah4jJ+gnKLIjKCM+Q==":"mbr-3.jpeg","8lvp9ISHPOav0iH8GHzE5A==":"mbr-596x397.jpg","UHlXa45jkpJnL4ssar7C0g==":"%D0%BF%D0%BE%D1%80%D1%82%D1%80%D0%B5%D1%82-495x863.jpeg","HVRTWipvMiA9DpL2fL/c9A==":"%D0%BF%D0%BE%D1%80%D1%82%D1%80%D0%B5%D1%82-495x863.jpeg","I363GqDHHbA7dvWNPHbM8A==":"%D1%83%D0%BD%D0%B8%D0%B2%D0%B5%D1%80-596x447.png","K8U/IlQPpRcLDRxjQDa/+g==":"%D1%80%D0%B0%D0%B1%D0%BE%D1%82%D0%B0-596x447.png","FuPp/ubOR2lyJhplKKe3VQ==":"%D0%BF%D0%B8%D0%BA%D0%BD%D0%B8%D0%BA-596x447.png","M0iWwQXl7REXjCkJ2m2JgA==":"%D0%B4%D0%BE%D0%BC%20%D1%81%20%D0%BA%D0%BE%D1%82%D0%BE%D0%BC-596x447.png","uhB7RF5n+2Sk0EjrV66ZUQ==":"%D1%84%D0%BE%D1%82%D0%BE%D0%B3%D1%80%D0%B0%D1%84-1256x942.png","4uAKle7Kry9+Wqyv42patA==":"%D1%83%D0%BD%D0%B8%D0%B2%D0%B5%D1%80-596x447.png","C5h9yxAgwJV5+oHS5PLjgQ==":"%D1%80%D0%B0%D0%B1%D0%BE%D1%82%D0%B0-596x447.png","YhxII3/3raikNISb6YRx0Q==":"%D0%BF%D0%B8%D0%BA%D0%BD%D0%B8%D0%BA-596x447.png","z1x9J9ZxwWlr4iqzI3ScVg==":"%D0%BF%D0%B8%D0%BA%D0%BD%D0%B8%D0%BA-1600x1200.png","0QWxjHm+sZEjMTc92hPb4Q==":"%D0%B4%D0%BE%D0%BC%20%D1%81%20%D0%BA%D0%BE%D1%82%D0%BE%D0%BC-1600x1200.png","iTT+1rZBH1EfnN+G3HM9Tw==":"1-1280x960.jpg","xGdH3yLdGbECkr8E4ywM9A==":"2-421x421.jpg","XbWQ/CmLdLLJNoG0zKcyVw==":"2-421x421.jpeg","IxXMrxS2Y2kXr9RNyIuv7g==":"2-1-421x421.jpeg","4Q+9qsy0UF+4RP/H0YSIYA==":"2-2-421x421.jpeg","CsGyL3xBWB/w4B8a0iO67w==":"2-3-421x421.jpeg","mbIdcvqW36AHvKSJNqeFew==":"2-4-421x421.jpeg","SL0NUnUtxqAbrdm+uFCn8g==":"2%202-421x311.jpg","rQfnAUnVZqablf8UWSfuYg==":"3-612x405.jpg","AuiIhInKSsmwJHshX+4D2g==":"4-640x480.jpg","1ygWCYQ/SSkiZ8LMtMmIDg==":"4%202-640x435.jpg","Mk75wVdcbDzBnsNMz1ixig==":"2%202-421x311.jpeg","HT8yWbhVPtwWIL0nkTlMLw==":"4%202-640x435.jpeg","HWhjZ7S8Ck35UuckNr81cw==":"5-615x410.jpg","DNwL6qu8qJxY9Lyw1mM0Uw==":"6-699x874.jpeg","k1AB6Ktc1D/0zdi+P0r6lw==":"6-1-699x874.jpeg","1nxjbUPXwbDM9J6omny2oA==":"7-750x751.jpg","bPkGTEm5mW7IaeSRsLce8w==":"8-950x633.jpg","Bw2nH/2EMsD7fEeVwHnK7g==":"7-750x751.jpeg","AGy0HCjOTxSIHlMjwS5K0A==":"7-1-750x751.jpeg","X7ZzZf6Vlv/JRRLopoQfYg==":"9-980x1146.jpg","WHkT5/ic+aux3twRDyibJw==":"10-1288x966.jpg","o1QHJDUb0bL0UmUdzVHFVg==":"9-980x1146.jpeg","6kumrMM2bn8lO6AC0Xo0OA==":"9-1-980x1146.jpeg","zCANiJtWlsP4skItlcXk/Q==":"%D0%B4%D0%B5%D0%BC%D0%BA%D0%B0-801x404.jpg","j314yoxDyWhBAudsFi10TQ==":"%D1%80%D0%B0%D0%B1%D0%BE%D1%82%D0%B0-1600x1200.png","2FlWnTtA82wpSYFAco9pAQ==":"%D1%83%D0%BD%D0%B8%D0%B2%D0%B5%D1%80-886x665.png","TROZT3aIcJZzniHvIQGv6A==":"%D1%80%D0%B0%D0%B1%D0%BE%D1%82%D0%B0-886x665.png","yTV+eDHYaD7JvMwJ+dlYRw==":"%D0%BF%D0%B8%D0%BA%D0%BD%D0%B8%D0%BA-886x665.png","wwNx3zoSGLUKMVtir1gugg==":"%D0%B4%D0%BE%D0%BC%20%D1%81%20%D0%BA%D0%BE%D1%82%D0%BE%D0%BC-886x665.png","tNZ9jT9uzNspvpwVISm7lg==":"%D1%83%D0%BD%D0%B8%D0%B2%D0%B5%D1%80-1256x942.png","DVHGEtn44M/kyf4rjaIU1w==":"%D1%80%D0%B0%D0%B1%D0%BE%D1%82%D0%B0-1256x942.png","U2b0Ebzjg6XY2M3UaPcYKw==":"%D0%BF%D0%B8%D0%BA%D0%BD%D0%B8%D0%BA-1256x942.png","8UczwOd41o0G0KJClQmMQQ==":"%D0%B4%D0%BE%D0%BC%20%D1%81%20%D0%BA%D0%BE%D1%82%D0%BE%D0%BC-1256x942.png","2wpTFZwaHDA0zpYwOJjXaw==":"%D1%83%D0%BD%D0%B8%D0%B2%D0%B5%D1%80-1256x942.jpg","V/B3sQ6AXn1GBqN14MNUWA==":"%D1%84%D0%BE%D1%82%D0%BE%D0%B3%D1%80%D0%B0%D1%84-1256x942.jpg","LnxMBymvFBgTvet0VE4lVw==":"%D1%80%D0%B0%D0%B1%D0%BE%D1%82%D0%B0-1256x942.jpg","0P14OUQP8GfwHfoYXm2a/w==":"%D0%BF%D0%B8%D0%BA%D0%BD%D0%B8%D0%BA-1256x942.jpg","lLgQWiE0Bdg5TyksenzvIQ==":"%D0%B4%D0%BE%D0%BC%20%D1%81%20%D0%BA%D0%BE%D1%82%D0%BE%D0%BC-1256x942.jpg","sQajjKgJS78nwAJbTzC/sA==":"10-1288x966.jpeg","VbE/AqQwF6fx5c6n32MpXA==":"1-1280x960.jpeg","1YpIVGkZ+gmMkyYeN0X1vw==":"%D0%BF%D0%BE%D1%80%D1%82%D1%80%D0%B5%D1%82-495x863.jpg","dXJwqnFop2VPTMsNoJMabA==":"%D1%83%D0%BD%D0%B8%D0%B2%D0%B5%D1%80-1256x942.jpg","joJ0CqiuIMwvLWd6FM/t4Q==":"%D1%80%D0%B0%D0%B1%D0%BE%D1%82%D0%B0-1256x942.jpg","ewuzTu1S4XvMtZWy2aGCAg==":"%D0%BF%D0%B8%D0%BA%D0%BD%D0%B8%D0%BA-1256x942.jpg","oC5d0cDV6m1U4yKMfUajvA==":"%D0%B4%D0%BE%D0%BC%20%D1%81%20%D0%BA%D0%BE%D1%82%D0%BE%D0%BC-1256x942.jpg","DlDZc4ubyGxwqQfmNg3BaA==":"%D1%84%D0%BE%D1%82%D0%BE%D0%B3%D1%80%D0%B0%D1%84-1256x942.jpg","WNQPKjtSuPXF0P6fxHJWCw==":"%D0%B4%D0%B5%D0%BC%D0%BA%D0%B0-801x404.jpg"}